chalk/__init__.py
chalk/_version.py
chalk/cli.py
chalk/importer.py
chalk/prompts.py
chalk/py.typed
chalk/state.py
chalk/_autosql/__init__.py
chalk/_autosql/autosql.py
chalk/_expression/__init__.py
chalk/_expression/converter.py
chalk/_gen/__init__.py
chalk/_gen/chalk/__init__.py
chalk/_gen/chalk/aggregate/__init__.py
chalk/_gen/chalk/aggregate/v1/__init__.py
chalk/_gen/chalk/aggregate/v1/backfill_pb2.py
chalk/_gen/chalk/aggregate/v1/backfill_pb2.pyi
chalk/_gen/chalk/aggregate/v1/backfill_pb2_grpc.py
chalk/_gen/chalk/aggregate/v1/backfill_pb2_grpc.pyi
chalk/_gen/chalk/aggregate/v1/service_pb2.py
chalk/_gen/chalk/aggregate/v1/service_pb2.pyi
chalk/_gen/chalk/aggregate/v1/service_pb2_grpc.py
chalk/_gen/chalk/aggregate/v1/service_pb2_grpc.pyi
chalk/_gen/chalk/aggregate/v1/timeseries_pb2.py
chalk/_gen/chalk/aggregate/v1/timeseries_pb2.pyi
chalk/_gen/chalk/aggregate/v1/timeseries_pb2_grpc.py
chalk/_gen/chalk/aggregate/v1/timeseries_pb2_grpc.pyi
chalk/_gen/chalk/arrow/__init__.py
chalk/_gen/chalk/arrow/v1/__init__.py
chalk/_gen/chalk/arrow/v1/arrow_pb2.py
chalk/_gen/chalk/arrow/v1/arrow_pb2.pyi
chalk/_gen/chalk/arrow/v1/arrow_pb2_grpc.py
chalk/_gen/chalk/arrow/v1/arrow_pb2_grpc.pyi
chalk/_gen/chalk/artifacts/__init__.py
chalk/_gen/chalk/artifacts/v1/__init__.py
chalk/_gen/chalk/artifacts/v1/cdc_pb2.py
chalk/_gen/chalk/artifacts/v1/cdc_pb2.pyi
chalk/_gen/chalk/artifacts/v1/cdc_pb2_grpc.py
chalk/_gen/chalk/artifacts/v1/cdc_pb2_grpc.pyi
chalk/_gen/chalk/artifacts/v1/chart_pb2.py
chalk/_gen/chalk/artifacts/v1/chart_pb2.pyi
chalk/_gen/chalk/artifacts/v1/chart_pb2_grpc.py
chalk/_gen/chalk/artifacts/v1/chart_pb2_grpc.pyi
chalk/_gen/chalk/artifacts/v1/cron_query_pb2.py
chalk/_gen/chalk/artifacts/v1/cron_query_pb2.pyi
chalk/_gen/chalk/artifacts/v1/cron_query_pb2_grpc.py
chalk/_gen/chalk/artifacts/v1/cron_query_pb2_grpc.pyi
chalk/_gen/chalk/artifacts/v1/deployment_pb2.py
chalk/_gen/chalk/artifacts/v1/deployment_pb2.pyi
chalk/_gen/chalk/artifacts/v1/deployment_pb2_grpc.py
chalkpy-2.97.2.dist-info/METADATA
chalkpy-2.97.2.dist-info/WHEEL
chalkpy-2.97.2.dist-info/entry_points.txt
chalkpy-2.97.2.dist-info/top_level.txt
chalkpy-2.97.2.dist-info/RECORD
