Metadata-Version: 2.4
Name: chalkpy
Version: 2.97.2
Summary: Python SDK for Chalk
Author: Chalk AI, Inc.
Project-URL: Homepage, https://chalk.ai
Project-URL: Documentation, https://docs.chalk.ai
Project-URL: Changelog, https://docs.chalk.ai/docs/changelog
Classifier: Programming Language :: Python :: 3
Classifier: Programming Language :: Python :: 3.10
Classifier: Programming Language :: Python :: 3.11
Classifier: Programming Language :: Python :: 3.12
Classifier: Programming Language :: Python
Classifier: Typing :: Typed
Classifier: Topic :: Scientific/Engineering :: Artificial Intelligence
Classifier: Topic :: Scientific/Engineering :: Information Analysis
Classifier: Topic :: Software Development :: Code Generators
Classifier: Topic :: Software Development :: Libraries :: Application Frameworks
Classifier: Topic :: Software Development :: Libraries :: Python Modules
Requires-Python: <3.13,>=3.10
Requires-Dist: attrs>=21.3.0
Requires-Dist: cattrs<25,>=22.1.0
Requires-Dist: dataclasses_json>=0.5.7
Requires-Dist: executing<3,>=1.2.0
Requires-Dist: googleapis-common-protos>=1.56.0
Requires-Dist: grpcio<2,>=1.63.0
Requires-Dist: ipywidgets>=8.0.6
Requires-Dist: isodate<0.8,>=0.6.1
Requires-Dist: numpy<3
Requires-Dist: orjson
Requires-Dist: pandas<2.3,>=1.5.1
Requires-Dist: protobuf<6,>=4.25
Requires-Dist: pyarrow>=16.1.0
Requires-Dist: pydantic<3,>=1.0.0
Requires-Dist: pyopenssl>=23.2.0
Requires-Dist: python-dateutil<3,>=2.8.0
Requires-Dist: pyyaml<7,>=6.0
Requires-Dist: requests<2.33.0,>=2.31
Requires-Dist: rich>=13.3.5
Requires-Dist: tenacity
Requires-Dist: tqdm
Requires-Dist: typing_extensions>=4.0.0
Provides-Extra: base
Provides-Extra: dev
Requires-Dist: boto3-stubs[s3]; extra == "dev"
Requires-Dist: grpc-stubs; extra == "dev"
Requires-Dist: pendulum; extra == "dev"
Requires-Dist: pre-commit; extra == "dev"
Requires-Dist: pytest-asyncio>=0.24.0; extra == "dev"
Requires-Dist: pytest-env; extra == "dev"
Requires-Dist: pytest-timeout; extra == "dev"
Requires-Dist: pytest-xdist; extra == "dev"
Requires-Dist: pytest; extra == "dev"
Requires-Dist: python-dotenv; extra == "dev"
Requires-Dist: sqlalchemy2-stubs; extra == "dev"
Requires-Dist: sqlglot<21.2.0,>=19.0.0; extra == "dev"
Requires-Dist: types-protobuf<6; extra == "dev"
Requires-Dist: types-psycopg2; extra == "dev"
Requires-Dist: types-pymysql; extra == "dev"
Requires-Dist: types-pyyaml; extra == "dev"
Requires-Dist: types-requests; extra == "dev"
Provides-Extra: runtime
Requires-Dist: adlfs; extra == "runtime"
Requires-Dist: duckdb<1.2.0,>=0.6; extra == "runtime"
Requires-Dist: fsspec; extra == "runtime"
Requires-Dist: gcsfs; extra == "runtime"
Requires-Dist: google-auth; extra == "runtime"
Requires-Dist: google-cloud-storage; extra == "runtime"
Requires-Dist: s3fs; extra == "runtime"
Requires-Dist: python-json-logger<4.0.0,>=3.0.0; extra == "runtime"
Requires-Dist: sqlglot<21.2.0,>=19.0.0; extra == "runtime"
Requires-Dist: polars[timezone]!=1.0,!=1.1,!=1.10,!=1.11,!=1.12,!=1.13,!=1.14,!=1.15,!=1.16,!=1.17,!=1.18,!=1.19,!=1.2,!=1.20,!=1.21,!=1.22,!=1.23,!=1.24,!=1.25,!=1.26,!=1.27,!=1.28,!=1.29,!=1.3,!=1.30,!=1.31,!=1.32,!=1.4,!=1.5,!=1.6,!=1.7,!=1.8,!=1.9,<1.33.1,>=0.17.2; extra == "runtime"
Provides-Extra: openai
Requires-Dist: openai<1.53,>=1.3.2; extra == "openai"
Requires-Dist: httpx<0.28.0; extra == "openai"
Requires-Dist: tiktoken<0.9,>=0.5.1; extra == "openai"
Provides-Extra: cohere
Requires-Dist: cohere==5.11.4; extra == "cohere"
Provides-Extra: vertexai
Requires-Dist: google-cloud-aiplatform<1.76.0; extra == "vertexai"
Provides-Extra: sentence-transformers
Requires-Dist: sentence-transformers; extra == "sentence-transformers"
Provides-Extra: sql
Requires-Dist: sqlalchemy[asyncio]<2,>=1.4.26; extra == "sql"
Requires-Dist: adlfs; extra == "sql"
Requires-Dist: duckdb<1.2.0,>=0.6; extra == "sql"
Requires-Dist: fsspec; extra == "sql"
Requires-Dist: gcsfs; extra == "sql"
Requires-Dist: google-auth; extra == "sql"
Requires-Dist: google-cloud-storage; extra == "sql"
Requires-Dist: polars[timezone]!=1.0,!=1.1,!=1.10,!=1.11,!=1.12,!=1.13,!=1.14,!=1.15,!=1.16,!=1.17,!=1.18,!=1.19,!=1.2,!=1.20,!=1.21,!=1.22,!=1.23,!=1.24,!=1.25,!=1.26,!=1.27,!=1.28,!=1.29,!=1.3,!=1.30,!=1.31,!=1.32,!=1.4,!=1.5,!=1.6,!=1.7,!=1.8,!=1.9,<1.33.1,>=0.17.2; extra == "sql"
Requires-Dist: python-json-logger<4.0.0,>=3.0.0; extra == "sql"
Requires-Dist: s3fs; extra == "sql"
Requires-Dist: sqlglot<21.2.0,>=19.0.0; extra == "sql"
Provides-Extra: athena
Requires-Dist: PyAthena>=3.0.0; extra == "athena"
Requires-Dist: adlfs; extra == "athena"
Requires-Dist: duckdb<1.2.0,>=0.6; extra == "athena"
Requires-Dist: fsspec; extra == "athena"
Requires-Dist: gcsfs; extra == "athena"
Requires-Dist: google-auth; extra == "athena"
Requires-Dist: google-cloud-storage; extra == "athena"
Requires-Dist: polars[timezone]!=1.0,!=1.1,!=1.10,!=1.11,!=1.12,!=1.13,!=1.14,!=1.15,!=1.16,!=1.17,!=1.18,!=1.19,!=1.2,!=1.20,!=1.21,!=1.22,!=1.23,!=1.24,!=1.25,!=1.26,!=1.27,!=1.28,!=1.29,!=1.3,!=1.30,!=1.31,!=1.32,!=1.4,!=1.5,!=1.6,!=1.7,!=1.8,!=1.9,<1.33.1,>=0.17.2; extra == "athena"
Requires-Dist: python-json-logger<4.0.0,>=3.0.0; extra == "athena"
Requires-Dist: s3fs; extra == "athena"
Requires-Dist: sqlalchemy[asyncio]<2,>=1.4.26; extra == "athena"
Requires-Dist: sqlglot<21.2.0,>=19.0.0; extra == "athena"
Provides-Extra: bigquery
Requires-Dist: sqlalchemy-bigquery<1.12,>=1.5.0; extra == "bigquery"
Requires-Dist: google-cloud-bigquery<4,>=3.25.0; extra == "bigquery"
Requires-Dist: google-cloud-bigquery-storage<2.28,>=2.22.0; extra == "bigquery"
Requires-Dist: adlfs; extra == "bigquery"
Requires-Dist: duckdb<1.2.0,>=0.6; extra == "bigquery"
Requires-Dist: fsspec; extra == "bigquery"
Requires-Dist: gcsfs; extra == "bigquery"
Requires-Dist: google-auth; extra == "bigquery"
Requires-Dist: google-cloud-storage; extra == "bigquery"
Requires-Dist: polars[timezone]!=1.0,!=1.1,!=1.10,!=1.11,!=1.12,!=1.13,!=1.14,!=1.15,!=1.16,!=1.17,!=1.18,!=1.19,!=1.2,!=1.20,!=1.21,!=1.22,!=1.23,!=1.24,!=1.25,!=1.26,!=1.27,!=1.28,!=1.29,!=1.3,!=1.30,!=1.31,!=1.32,!=1.4,!=1.5,!=1.6,!=1.7,!=1.8,!=1.9,<1.33.1,>=0.17.2; extra == "bigquery"
Requires-Dist: python-json-logger<4.0.0,>=3.0.0; extra == "bigquery"
Requires-Dist: s3fs; extra == "bigquery"
Requires-Dist: sqlalchemy[asyncio]<2,>=1.4.26; extra == "bigquery"
Requires-Dist: sqlglot<21.2.0,>=19.0.0; extra == "bigquery"
Provides-Extra: clickhouse
Requires-Dist: clickhouse-sqlalchemy; extra == "clickhouse"
Requires-Dist: clickhouse-driver; extra == "clickhouse"
Requires-Dist: adlfs; extra == "clickhouse"
Requires-Dist: duckdb<1.2.0,>=0.6; extra == "clickhouse"
Requires-Dist: fsspec; extra == "clickhouse"
Requires-Dist: gcsfs; extra == "clickhouse"
Requires-Dist: google-auth; extra == "clickhouse"
Requires-Dist: google-cloud-storage; extra == "clickhouse"
Requires-Dist: polars[timezone]!=1.0,!=1.1,!=1.10,!=1.11,!=1.12,!=1.13,!=1.14,!=1.15,!=1.16,!=1.17,!=1.18,!=1.19,!=1.2,!=1.20,!=1.21,!=1.22,!=1.23,!=1.24,!=1.25,!=1.26,!=1.27,!=1.28,!=1.29,!=1.3,!=1.30,!=1.31,!=1.32,!=1.4,!=1.5,!=1.6,!=1.7,!=1.8,!=1.9,<1.33.1,>=0.17.2; extra == "clickhouse"
Requires-Dist: python-json-logger<4.0.0,>=3.0.0; extra == "clickhouse"
Requires-Dist: s3fs; extra == "clickhouse"
Requires-Dist: sqlalchemy[asyncio]<2,>=1.4.26; extra == "clickhouse"
Requires-Dist: sqlglot<21.2.0,>=19.0.0; extra == "clickhouse"
Provides-Extra: spanner
Requires-Dist: sqlalchemy-spanner<1.12.0; extra == "spanner"
Requires-Dist: google-auth; extra == "spanner"
Requires-Dist: adlfs; extra == "spanner"
Requires-Dist: duckdb<1.2.0,>=0.6; extra == "spanner"
Requires-Dist: fsspec; extra == "spanner"
Requires-Dist: gcsfs; extra == "spanner"
Requires-Dist: google-auth; extra == "spanner"
Requires-Dist: google-cloud-storage; extra == "spanner"
Requires-Dist: polars[timezone]!=1.0,!=1.1,!=1.10,!=1.11,!=1.12,!=1.13,!=1.14,!=1.15,!=1.16,!=1.17,!=1.18,!=1.19,!=1.2,!=1.20,!=1.21,!=1.22,!=1.23,!=1.24,!=1.25,!=1.26,!=1.27,!=1.28,!=1.29,!=1.3,!=1.30,!=1.31,!=1.32,!=1.4,!=1.5,!=1.6,!=1.7,!=1.8,!=1.9,<1.33.1,>=0.17.2; extra == "spanner"
Requires-Dist: python-json-logger<4.0.0,>=3.0.0; extra == "spanner"
Requires-Dist: s3fs; extra == "spanner"
Requires-Dist: sqlalchemy[asyncio]<2,>=1.4.26; extra == "spanner"
Requires-Dist: sqlglot<21.2.0,>=19.0.0; extra == "spanner"
Provides-Extra: postgresql
Requires-Dist: psycopg2<3,>=2.9.4; extra == "postgresql"
Requires-Dist: psycopg[binary]<3.3,>=3.1.9; extra == "postgresql"
Requires-Dist: packaging; extra == "postgresql"
Requires-Dist: adlfs; extra == "postgresql"
Requires-Dist: duckdb<1.2.0,>=0.6; extra == "postgresql"
Requires-Dist: fsspec; extra == "postgresql"
Requires-Dist: gcsfs; extra == "postgresql"
Requires-Dist: google-auth; extra == "postgresql"
Requires-Dist: google-cloud-storage; extra == "postgresql"
Requires-Dist: polars[timezone]!=1.0,!=1.1,!=1.10,!=1.11,!=1.12,!=1.13,!=1.14,!=1.15,!=1.16,!=1.17,!=1.18,!=1.19,!=1.2,!=1.20,!=1.21,!=1.22,!=1.23,!=1.24,!=1.25,!=1.26,!=1.27,!=1.28,!=1.29,!=1.3,!=1.30,!=1.31,!=1.32,!=1.4,!=1.5,!=1.6,!=1.7,!=1.8,!=1.9,<1.33.1,>=0.17.2; extra == "postgresql"
Requires-Dist: python-json-logger<4.0.0,>=3.0.0; extra == "postgresql"
Requires-Dist: s3fs; extra == "postgresql"
Requires-Dist: sqlalchemy[asyncio]<2,>=1.4.26; extra == "postgresql"
Requires-Dist: sqlglot<21.2.0,>=19.0.0; extra == "postgresql"
Provides-Extra: snowflake
Requires-Dist: cryptography<42.0.0; extra == "snowflake"
Requires-Dist: snowflake-connector-python<4,>=3.12.4; extra == "snowflake"
Requires-Dist: snowflake-sqlalchemy<1.7,>=1.5.0; extra == "snowflake"
Requires-Dist: adlfs; extra == "snowflake"
Requires-Dist: duckdb<1.2.0,>=0.6; extra == "snowflake"
Requires-Dist: fsspec; extra == "snowflake"
Requires-Dist: gcsfs; extra == "snowflake"
Requires-Dist: google-auth; extra == "snowflake"
Requires-Dist: google-cloud-storage; extra == "snowflake"
Requires-Dist: polars[timezone]!=1.0,!=1.1,!=1.10,!=1.11,!=1.12,!=1.13,!=1.14,!=1.15,!=1.16,!=1.17,!=1.18,!=1.19,!=1.2,!=1.20,!=1.21,!=1.22,!=1.23,!=1.24,!=1.25,!=1.26,!=1.27,!=1.28,!=1.29,!=1.3,!=1.30,!=1.31,!=1.32,!=1.4,!=1.5,!=1.6,!=1.7,!=1.8,!=1.9,<1.33.1,>=0.17.2; extra == "snowflake"
Requires-Dist: python-json-logger<4.0.0,>=3.0.0; extra == "snowflake"
Requires-Dist: s3fs; extra == "snowflake"
Requires-Dist: sqlalchemy[asyncio]<2,>=1.4.26; extra == "snowflake"
Requires-Dist: sqlglot<21.2.0,>=19.0.0; extra == "snowflake"
Provides-Extra: sqlite
Requires-Dist: aiosqlite<0.21,>=0.19.0; extra == "sqlite"
Requires-Dist: adlfs; extra == "sqlite"
Requires-Dist: duckdb<1.2.0,>=0.6; extra == "sqlite"
Requires-Dist: fsspec; extra == "sqlite"
Requires-Dist: gcsfs; extra == "sqlite"
Requires-Dist: google-auth; extra == "sqlite"
Requires-Dist: google-cloud-storage; extra == "sqlite"
Requires-Dist: polars[timezone]!=1.0,!=1.1,!=1.10,!=1.11,!=1.12,!=1.13,!=1.14,!=1.15,!=1.16,!=1.17,!=1.18,!=1.19,!=1.2,!=1.20,!=1.21,!=1.22,!=1.23,!=1.24,!=1.25,!=1.26,!=1.27,!=1.28,!=1.29,!=1.3,!=1.30,!=1.31,!=1.32,!=1.4,!=1.5,!=1.6,!=1.7,!=1.8,!=1.9,<1.33.1,>=0.17.2; extra == "sqlite"
Requires-Dist: python-json-logger<4.0.0,>=3.0.0; extra == "sqlite"
Requires-Dist: s3fs; extra == "sqlite"
Requires-Dist: sqlalchemy[asyncio]<2,>=1.4.26; extra == "sqlite"
Requires-Dist: sqlglot<21.2.0,>=19.0.0; extra == "sqlite"
Provides-Extra: redshift
Requires-Dist: chalk-sqlalchemy-redshift<0.9,>=0.8.11; extra == "redshift"
Requires-Dist: redshift_connector<2.2,>=2.0.909; extra == "redshift"
Requires-Dist: boto3; extra == "redshift"
Requires-Dist: adlfs; extra == "redshift"
Requires-Dist: duckdb<1.2.0,>=0.6; extra == "redshift"
Requires-Dist: fsspec; extra == "redshift"
Requires-Dist: gcsfs; extra == "redshift"
Requires-Dist: google-auth; extra == "redshift"
Requires-Dist: google-cloud-storage; extra == "redshift"
Requires-Dist: packaging; extra == "redshift"
Requires-Dist: polars[timezone]!=1.0,!=1.1,!=1.10,!=1.11,!=1.12,!=1.13,!=1.14,!=1.15,!=1.16,!=1.17,!=1.18,!=1.19,!=1.2,!=1.20,!=1.21,!=1.22,!=1.23,!=1.24,!=1.25,!=1.26,!=1.27,!=1.28,!=1.29,!=1.3,!=1.30,!=1.31,!=1.32,!=1.4,!=1.5,!=1.6,!=1.7,!=1.8,!=1.9,<1.33.1,>=0.17.2; extra == "redshift"
Requires-Dist: psycopg2<3,>=2.9.4; extra == "redshift"
Requires-Dist: psycopg[binary]<3.3,>=3.1.9; extra == "redshift"
Requires-Dist: python-json-logger<4.0.0,>=3.0.0; extra == "redshift"
Requires-Dist: s3fs; extra == "redshift"
Requires-Dist: sqlalchemy[asyncio]<2,>=1.4.26; extra == "redshift"
Requires-Dist: sqlglot<21.2.0,>=19.0.0; extra == "redshift"
Provides-Extra: mssql
Requires-Dist: azure-identity<2,>=1.12.0; extra == "mssql"
Requires-Dist: pyodbc<6,>=4.0.0; extra == "mssql"
Requires-Dist: adlfs; extra == "mssql"
Requires-Dist: duckdb<1.2.0,>=0.6; extra == "mssql"
Requires-Dist: fsspec; extra == "mssql"
Requires-Dist: gcsfs; extra == "mssql"
Requires-Dist: google-auth; extra == "mssql"
Requires-Dist: google-cloud-storage; extra == "mssql"
Requires-Dist: polars[timezone]!=1.0,!=1.1,!=1.10,!=1.11,!=1.12,!=1.13,!=1.14,!=1.15,!=1.16,!=1.17,!=1.18,!=1.19,!=1.2,!=1.20,!=1.21,!=1.22,!=1.23,!=1.24,!=1.25,!=1.26,!=1.27,!=1.28,!=1.29,!=1.3,!=1.30,!=1.31,!=1.32,!=1.4,!=1.5,!=1.6,!=1.7,!=1.8,!=1.9,<1.33.1,>=0.17.2; extra == "mssql"
Requires-Dist: python-json-logger<4.0.0,>=3.0.0; extra == "mssql"
Requires-Dist: s3fs; extra == "mssql"
Requires-Dist: sqlalchemy[asyncio]<2,>=1.4.26; extra == "mssql"
Requires-Dist: sqlglot<21.2.0,>=19.0.0; extra == "mssql"
Provides-Extra: mysql
Requires-Dist: pymysql<2,>=1.0.2; extra == "mysql"
Requires-Dist: aiomysql<0.3,>=0.1.1; extra == "mysql"
Requires-Dist: adlfs; extra == "mysql"
Requires-Dist: duckdb<1.2.0,>=0.6; extra == "mysql"
Requires-Dist: fsspec; extra == "mysql"
Requires-Dist: gcsfs; extra == "mysql"
Requires-Dist: google-auth; extra == "mysql"
Requires-Dist: google-cloud-storage; extra == "mysql"
Requires-Dist: polars[timezone]!=1.0,!=1.1,!=1.10,!=1.11,!=1.12,!=1.13,!=1.14,!=1.15,!=1.16,!=1.17,!=1.18,!=1.19,!=1.2,!=1.20,!=1.21,!=1.22,!=1.23,!=1.24,!=1.25,!=1.26,!=1.27,!=1.28,!=1.29,!=1.3,!=1.30,!=1.31,!=1.32,!=1.4,!=1.5,!=1.6,!=1.7,!=1.8,!=1.9,<1.33.1,>=0.17.2; extra == "mysql"
Requires-Dist: python-json-logger<4.0.0,>=3.0.0; extra == "mysql"
Requires-Dist: s3fs; extra == "mysql"
Requires-Dist: sqlalchemy[asyncio]<2,>=1.4.26; extra == "mysql"
Requires-Dist: sqlglot<21.2.0,>=19.0.0; extra == "mysql"
Provides-Extra: trino
Requires-Dist: trino[sqlalchemy]; extra == "trino"
Requires-Dist: adlfs; extra == "trino"
Requires-Dist: duckdb<1.2.0,>=0.6; extra == "trino"
Requires-Dist: fsspec; extra == "trino"
Requires-Dist: gcsfs; extra == "trino"
Requires-Dist: google-auth; extra == "trino"
Requires-Dist: google-cloud-storage; extra == "trino"
Requires-Dist: polars[timezone]!=1.0,!=1.1,!=1.10,!=1.11,!=1.12,!=1.13,!=1.14,!=1.15,!=1.16,!=1.17,!=1.18,!=1.19,!=1.2,!=1.20,!=1.21,!=1.22,!=1.23,!=1.24,!=1.25,!=1.26,!=1.27,!=1.28,!=1.29,!=1.3,!=1.30,!=1.31,!=1.32,!=1.4,!=1.5,!=1.6,!=1.7,!=1.8,!=1.9,<1.33.1,>=0.17.2; extra == "trino"
Requires-Dist: python-json-logger<4.0.0,>=3.0.0; extra == "trino"
Requires-Dist: s3fs; extra == "trino"
Requires-Dist: sqlalchemy[asyncio]<2,>=1.4.26; extra == "trino"
Requires-Dist: sqlglot<21.2.0,>=19.0.0; extra == "trino"
Provides-Extra: databricks
Requires-Dist: databricks-sql-connector<3.5,>=2.5.2; extra == "databricks"
Requires-Dist: databricks-sdk<1.0.0,>=0.29.0; extra == "databricks"
Requires-Dist: adlfs; extra == "databricks"
Requires-Dist: duckdb<1.2.0,>=0.6; extra == "databricks"
Requires-Dist: fsspec; extra == "databricks"
Requires-Dist: gcsfs; extra == "databricks"
Requires-Dist: google-auth; extra == "databricks"
Requires-Dist: google-cloud-storage; extra == "databricks"
Requires-Dist: polars[timezone]!=1.0,!=1.1,!=1.10,!=1.11,!=1.12,!=1.13,!=1.14,!=1.15,!=1.16,!=1.17,!=1.18,!=1.19,!=1.2,!=1.20,!=1.21,!=1.22,!=1.23,!=1.24,!=1.25,!=1.26,!=1.27,!=1.28,!=1.29,!=1.3,!=1.30,!=1.31,!=1.32,!=1.4,!=1.5,!=1.6,!=1.7,!=1.8,!=1.9,<1.33.1,>=0.17.2; extra == "databricks"
Requires-Dist: python-json-logger<4.0.0,>=3.0.0; extra == "databricks"
Requires-Dist: s3fs; extra == "databricks"
Requires-Dist: sqlalchemy[asyncio]<2,>=1.4.26; extra == "databricks"
Requires-Dist: sqlglot<21.2.0,>=19.0.0; extra == "databricks"
Provides-Extra: dynamodb
Requires-Dist: boto3; extra == "dynamodb"
Requires-Dist: pydynamodb<0.8,>=0.6; extra == "dynamodb"
Requires-Dist: adlfs; extra == "dynamodb"
Requires-Dist: duckdb<1.2.0,>=0.6; extra == "dynamodb"
Requires-Dist: fsspec; extra == "dynamodb"
Requires-Dist: gcsfs; extra == "dynamodb"
Requires-Dist: google-auth; extra == "dynamodb"
Requires-Dist: google-cloud-storage; extra == "dynamodb"
Requires-Dist: polars[timezone]!=1.0,!=1.1,!=1.10,!=1.11,!=1.12,!=1.13,!=1.14,!=1.15,!=1.16,!=1.17,!=1.18,!=1.19,!=1.2,!=1.20,!=1.21,!=1.22,!=1.23,!=1.24,!=1.25,!=1.26,!=1.27,!=1.28,!=1.29,!=1.3,!=1.30,!=1.31,!=1.32,!=1.4,!=1.5,!=1.6,!=1.7,!=1.8,!=1.9,<1.33.1,>=0.17.2; extra == "dynamodb"
Requires-Dist: python-json-logger<4.0.0,>=3.0.0; extra == "dynamodb"
Requires-Dist: s3fs; extra == "dynamodb"
Requires-Dist: sqlalchemy[asyncio]<2,>=1.4.26; extra == "dynamodb"
Requires-Dist: sqlglot<21.2.0,>=19.0.0; extra == "dynamodb"
Provides-Extra: tracing
Requires-Dist: opentelemetry-api>=1.29.0; extra == "tracing"
Requires-Dist: opentelemetry-sdk>=1.29.0; extra == "tracing"
Provides-Extra: all
Requires-Dist: PyAthena>=3.0.0; extra == "all"
Requires-Dist: adlfs; extra == "all"
Requires-Dist: aiomysql<0.3,>=0.1.1; extra == "all"
Requires-Dist: aiosqlite<0.21,>=0.19.0; extra == "all"
Requires-Dist: azure-identity<2,>=1.12.0; extra == "all"
Requires-Dist: boto3; extra == "all"
Requires-Dist: chalk-sqlalchemy-redshift<0.9,>=0.8.11; extra == "all"
Requires-Dist: clickhouse-driver; extra == "all"
Requires-Dist: clickhouse-sqlalchemy; extra == "all"
Requires-Dist: cohere==5.11.4; extra == "all"
Requires-Dist: cryptography<42.0.0; extra == "all"
Requires-Dist: databricks-sdk<1.0.0,>=0.29.0; extra == "all"
Requires-Dist: databricks-sql-connector<3.5,>=2.5.2; extra == "all"
Requires-Dist: duckdb<1.2.0,>=0.6; extra == "all"
Requires-Dist: fsspec; extra == "all"
Requires-Dist: gcsfs; extra == "all"
Requires-Dist: google-auth; extra == "all"
Requires-Dist: google-cloud-aiplatform<1.76.0; extra == "all"
Requires-Dist: google-cloud-bigquery-storage<2.28,>=2.22.0; extra == "all"
Requires-Dist: google-cloud-bigquery<4,>=3.25.0; extra == "all"
Requires-Dist: google-cloud-storage; extra == "all"
Requires-Dist: httpx<0.28.0; extra == "all"
Requires-Dist: openai<1.53,>=1.3.2; extra == "all"
Requires-Dist: opentelemetry-api>=1.29.0; extra == "all"
Requires-Dist: opentelemetry-sdk>=1.29.0; extra == "all"
Requires-Dist: packaging; extra == "all"
Requires-Dist: polars[timezone]!=1.0,!=1.1,!=1.10,!=1.11,!=1.12,!=1.13,!=1.14,!=1.15,!=1.16,!=1.17,!=1.18,!=1.19,!=1.2,!=1.20,!=1.21,!=1.22,!=1.23,!=1.24,!=1.25,!=1.26,!=1.27,!=1.28,!=1.29,!=1.3,!=1.30,!=1.31,!=1.32,!=1.4,!=1.5,!=1.6,!=1.7,!=1.8,!=1.9,<1.33.1,>=0.17.2; extra == "all"
Requires-Dist: psycopg2<3,>=2.9.4; extra == "all"
Requires-Dist: psycopg[binary]<3.3,>=3.1.9; extra == "all"
Requires-Dist: pydynamodb<0.8,>=0.6; extra == "all"
Requires-Dist: pymysql<2,>=1.0.2; extra == "all"
Requires-Dist: pyodbc<6,>=4.0.0; extra == "all"
Requires-Dist: python-json-logger<4.0.0,>=3.0.0; extra == "all"
Requires-Dist: redshift_connector<2.2,>=2.0.909; extra == "all"
Requires-Dist: s3fs; extra == "all"
Requires-Dist: snowflake-connector-python<4,>=3.12.4; extra == "all"
Requires-Dist: snowflake-sqlalchemy<1.7,>=1.5.0; extra == "all"
Requires-Dist: sqlalchemy-bigquery<1.12,>=1.5.0; extra == "all"
Requires-Dist: sqlalchemy-spanner<1.12.0; extra == "all"
Requires-Dist: sqlalchemy[asyncio]<2,>=1.4.26; extra == "all"
Requires-Dist: sqlglot<21.2.0,>=19.0.0; extra == "all"
Requires-Dist: tiktoken<0.9,>=0.5.1; extra == "all"
Requires-Dist: trino[sqlalchemy]; extra == "all"
Provides-Extra: polars
Requires-Dist: adlfs; extra == "polars"
Requires-Dist: duckdb<1.2.0,>=0.6; extra == "polars"
Requires-Dist: fsspec; extra == "polars"
Requires-Dist: gcsfs; extra == "polars"
Requires-Dist: google-auth; extra == "polars"
Requires-Dist: google-cloud-storage; extra == "polars"
Requires-Dist: polars[timezone]!=1.0,!=1.1,!=1.10,!=1.11,!=1.12,!=1.13,!=1.14,!=1.15,!=1.16,!=1.17,!=1.18,!=1.19,!=1.2,!=1.20,!=1.21,!=1.22,!=1.23,!=1.24,!=1.25,!=1.26,!=1.27,!=1.28,!=1.29,!=1.3,!=1.30,!=1.31,!=1.32,!=1.4,!=1.5,!=1.6,!=1.7,!=1.8,!=1.9,<1.33.1,>=0.17.2; extra == "polars"
Requires-Dist: python-json-logger<4.0.0,>=3.0.0; extra == "polars"
Requires-Dist: s3fs; extra == "polars"
Requires-Dist: sqlglot<21.2.0,>=19.0.0; extra == "polars"
